{
  "Vendor": "Dell",
  "ListType": "OutOfScope",
  "LastUpdated": "2026-07-16T08:01:39Z",
  "SourceUrl": "https://www.dell.com/support/kbdoc/en-us/000378734/microsoft-2011-secure-boot-certificates-expiration-for-out-of-scope-platforms-for-bios-updates",
  "RecordCount": 408,
  "Models": [
    "Embedded Box PC PC 5000",
    "Embedded Box PC PC 5000 OEM",
    "Inspiron 1100",
    "Inspiron 14 3452",
    "Inspiron 14 3467",
    "Inspiron 14 5439",
    "Inspiron 14 5458",
    "Inspiron 14 5459",
    "Inspiron 15 3552",
    "Inspiron 15 3558",
    "Inspiron 15 3565",
    "Inspiron 15 3567",
    "Inspiron 15 3573",
    "Inspiron 15 3576",
    "Inspiron 15 5555",
    "Inspiron 15 5558",
    "Inspiron 15 5559",
    "Inspiron 15 5565",
    "Inspiron 15 5566",
    "Inspiron 15 5567",
    "Inspiron 1525",
    "Inspiron 1545",
    "Inspiron 17 5755",
    "Inspiron 17 5765",
    "Inspiron 17 5767",
    "Inspiron 20 3052",
    "Inspiron 22 3275",
    "Inspiron 22 3277",
    "Inspiron 22 3280",
    "Inspiron 24 3455",
    "Inspiron 24 3464",
    "Inspiron 24 3475",
    "Inspiron 24 3477",
    "Inspiron 24 3480",
    "Inspiron 24 5459",
    "Inspiron 24 5475",
    "Inspiron 24 5477",
    "Inspiron 24 7459",
    "Inspiron 2500",
    "Inspiron 27 7777",
    "Inspiron 3168",
    "Inspiron 3169",
    "Inspiron 3179",
    "Inspiron 3180",
    "Inspiron 3181",
    "Inspiron 3181 2-in-1",
    "Inspiron 3185",
    "Inspiron 3195 2-in-1",
    "Inspiron 3250",
    "Inspiron 3252",
    "Inspiron 3442",
    "Inspiron 3443",
    "Inspiron 3470",
    "Inspiron 3471",
    "Inspiron 3472",
    "Inspiron 3480",
    "Inspiron 3481",
    "Inspiron 3482",
    "Inspiron 3493",
    "Inspiron 3531",
    "Inspiron 3542",
    "Inspiron 3580",
    "Inspiron 3581",
    "Inspiron 3582",
    "Inspiron 3583",
    "Inspiron 3584",
    "Inspiron 3585",
    "Inspiron 3590",
    "Inspiron 3593",
    "Inspiron 3595",
    "Inspiron 3647",
    "Inspiron 3650",
    "Inspiron 3668",
    "Inspiron 3670",
    "Inspiron 3671",
    "Inspiron 3780",
    "Inspiron 3781",
    "Inspiron 3785",
    "Inspiron 3790",
    "Inspiron 3793",
    "Inspiron 3847",
    "Inspiron 3880",
    "Inspiron 3881",
    "Inspiron 4000",
    "Inspiron 5300",
    "Inspiron 5301",
    "Inspiron 5310",
    "Inspiron 5368",
    "Inspiron 5370",
    "Inspiron 5378",
    "Inspiron 5379",
    "Inspiron 5390",
    "Inspiron 5391",
    "Inspiron 5405",
    "Inspiron 5406 2-in-1",
    "Inspiron 5408",
    "Inspiron 5409",
    "Inspiron 5410",
    "Inspiron 5415",
    "Inspiron 5418",
    "Inspiron 5480",
    "Inspiron 5481",
    "Inspiron 5482",
    "Inspiron 5485",
    "Inspiron 5485 2-in-1",
    "Inspiron 5488",
    "Inspiron 5490",
    "Inspiron 5490 All in One",
    "Inspiron 5491 2-in-1",
    "Inspiron 5491 All in One",
    "Inspiron 5493",
    "Inspiron 5498",
    "Inspiron 5501",
    "Inspiron 5502",
    "Inspiron 5505",
    "Inspiron 5508",
    "Inspiron 5515",
    "Inspiron 5547",
    "Inspiron 5548",
    "Inspiron 5568",
    "Inspiron 5570",
    "Inspiron 5575",
    "Inspiron 5576",
    "Inspiron 5577",
    "Inspiron 5578",
    "Inspiron 5579",
    "Inspiron 5580",
    "Inspiron 5582",
    "Inspiron 5583",
    "Inspiron 5584",
    "Inspiron 5585",
    "Inspiron 5590",
    "Inspiron 5591 2-in-1",
    "Inspiron 5593",
    "Inspiron 5594",
    "Inspiron 5598",
    "Inspiron 5676",
    "Inspiron 5680",
    "Inspiron 5770",
    "Inspiron 5775",
    "Inspiron 6000",
    "Inspiron 630M",
    "Inspiron 7300",
    "Inspiron 7300 2-in-1",
    "Inspiron 7306 2-in-1",
    "Inspiron 7359",
    "Inspiron 7370",
    "Inspiron 7373",
    "Inspiron 7375",
    "Inspiron 7380",
    "Inspiron 7386",
    "Inspiron 7390 2-in-1",
    "Inspiron 7391",
    "Inspiron 7391 2-in-1",
    "Inspiron 7405 2-in-1",
    "Inspiron 7460",
    "Inspiron 7467",
    "Inspiron 7472",
    "Inspiron 7486",
    "Inspiron 7490",
    "Inspiron 7500",
    "Inspiron 7500 2-in-1",
    "Inspiron 7506 2-in-1",
    "Inspiron 7510",
    "Inspiron 7548",
    "Inspiron 7559",
    "Inspiron 7560",
    "Inspiron 7567",
    "Inspiron 7568",
    "Inspiron 7570",
    "Inspiron 7572",
    "Inspiron 7573",
    "Inspiron 7577",
    "Inspiron 7579",
    "Inspiron 7580",
    "Inspiron 7586",
    "Inspiron 7590",
    "Inspiron 7590 2-in-1",
    "Inspiron 7591",
    "Inspiron 7591 2-in-1",
    "Inspiron 7610",
    "Inspiron 7706 2-in-1",
    "Inspiron 7773",
    "Inspiron 7778",
    "Inspiron 7779",
    "Inspiron 7786",
    "Inspiron 7790 All in One",
    "Inspiron 7791 2-in-1",
    "Inspiron 8000",
    "Inspiron 8600",
    "Inspiron N5010",
    "Inspiron XPS2",
    "Latitude 10",
    "Latitude 3189",
    "Latitude 3300",
    "Latitude 3380",
    "Latitude 3390",
    "Latitude 3460",
    "Latitude 3480",
    "Latitude 3490",
    "Latitude 3580",
    "Latitude 3590",
    "Latitude 5280",
    "Latitude 5285",
    "Latitude 5290",
    "Latitude 5290 2-in-1",
    "Latitude 5414 Rugged",
    "Latitude 5480",
    "Latitude 5490",
    "Latitude 5491",
    "Latitude 5495",
    "Latitude 5580",
    "Latitude 5590",
    "Latitude 5591",
    "Latitude 7275",
    "Latitude 7280",
    "Latitude 7285",
    "Latitude 7290",
    "Latitude 7380",
    "Latitude 7389",
    "Latitude 7390",
    "Latitude 7414 Rugged",
    "Latitude 7480",
    "Latitude 7490",
    "Latitude C600",
    "Latitude C610",
    "Latitude C640",
    "Latitude C810",
    "Latitude C840",
    "Latitude D410",
    "Latitude D430",
    "Latitude D505",
    "Latitude D510",
    "Latitude D600",
    "Latitude D610",
    "Latitude D620",
    "Latitude D630",
    "Latitude D800",
    "Latitude D810",
    "Latitude D820",
    "Latitude E5270",
    "Latitude E5470",
    "Latitude E5570",
    "Latitude E6400",
    "Latitude E6410",
    "Latitude E6510",
    "Latitude E6540",
    "Latitude E7240",
    "Latitude E7250",
    "Latitude E7270",
    "Latitude E7440",
    "Latitude E7450",
    "Latitude E7470",
    "Latitude LS",
    "Latitude ST",
    "Latitude XPI",
    "OptiPlex 170L",
    "OptiPlex 3020",
    "OptiPlex 3040",
    "OptiPlex 3046",
    "OptiPlex 3050",
    "OptiPlex 3050 All in One",
    "OptiPlex 3060",
    "OptiPlex 330",
    "OptiPlex 380",
    "OptiPlex 5050",
    "OptiPlex 5055",
    "OptiPlex 5060",
    "OptiPlex 5250 All in One",
    "OptiPlex 5260 All in One",
    "OptiPlex 7020",
    "OptiPlex 7040",
    "OptiPlex 7050",
    "OptiPlex 7060",
    "OptiPlex 7440 All in One",
    "OptiPlex 745",
    "OptiPlex 7450 All in One",
    "OptiPlex 7460 All in One",
    "OptiPlex 755",
    "OptiPlex 7760 All in One",
    "OptiPlex 790",
    "OptiPlex 9010",
    "OptiPlex 9020",
    "OptiPlex 980",
    "OptiPlex 990",
    "OptiPlex G1",
    "OptiPlex GX110",
    "OptiPlex GX200",
    "OptiPlex GX240",
    "OptiPlex GX260",
    "OptiPlex GX270",
    "OptiPlex GX280",
    "OptiPlex GX400",
    "OptiPlex GX520",
    "OptiPlex GX620",
    "OptiPlex GXI",
    "OptiPlex SX260",
    "OptiPlex SX280",
    "OptiPlex XE2",
    "Precision 3520",
    "Precision 3530",
    "Precision 5510",
    "Precision 5520",
    "Precision 5530",
    "Precision 5530 2-in-1",
    "Precision 7510",
    "Precision 7520",
    "Precision 7530",
    "Precision 7710",
    "Precision 7720",
    "Precision 7730",
    "Precision R7610",
    "Precision R7910",
    "Precision T1600",
    "Precision T3500",
    "Precision T3600",
    "Precision T5500",
    "Precision T5600",
    "Precision T5810",
    "Precision T7500",
    "Precision T7610",
    "Precision Tower 3420",
    "Precision Tower 3620",
    "Precision Tower 5810",
    "Precision Tower 7810",
    "Precision Tower 7910",
    "Precision WS350",
    "Precision WS370",
    "Precision WS380",
    "Precision WS450",
    "Precision WS490",
    "Precision WS670",
    "Precision WST7400",
    "Vostro 14 3458",
    "Vostro 14 3468",
    "Vostro 14 3478",
    "Vostro 14 5415",
    "Vostro 14 5459",
    "Vostro 14 5468",
    "Vostro 15 3558",
    "Vostro 15 3568",
    "Vostro 15 3578",
    "Vostro 15 5515",
    "Vostro 15 5568",
    "Vostro 200",
    "Vostro 3070",
    "Vostro 3250",
    "Vostro 3268",
    "Vostro 3470",
    "Vostro 3471",
    "Vostro 3481",
    "Vostro 3490",
    "Vostro 3491",
    "Vostro 3580",
    "Vostro 3581",
    "Vostro 3582",
    "Vostro 3583",
    "Vostro 3584",
    "Vostro 3590",
    "Vostro 3591",
    "Vostro 3653",
    "Vostro 3668",
    "Vostro 3669",
    "Vostro 3670",
    "Vostro 3671",
    "Vostro 5090",
    "Vostro 5300",
    "Vostro 5310",
    "Vostro 5370",
    "Vostro 5390",
    "Vostro 5391",
    "Vostro 5401",
    "Vostro 5471",
    "Vostro 5480",
    "Vostro 5481",
    "Vostro 5490",
    "Vostro 5501",
    "Vostro 5581",
    "Vostro 5590",
    "Vostro 5880",
    "Vostro 5890",
    "Vostro 7510",
    "Vostro 7590",
    "XPS 13 7390",
    "XPS 13 7390 2-in-1",
    "XPS 13 9300",
    "XPS 13 9310 2-in-1",
    "XPS 13 9343",
    "XPS 13 9360",
    "XPS 13 9365",
    "XPS 13 9370",
    "XPS 13 9380",
    "XPS 13 L321X",
    "XPS 13 L322X",
    "XPS 15 7590",
    "XPS 15 9560",
    "XPS 15 9570",
    "XPS 15 9575 2-in-1",
    "XPS 27 All in One",
    "XPS 410",
    "XPS 8910",
    "XPS 8920",
    "XPS 8930",
    "XPS 8940",
    "XPS 9350",
    "XPS 9550",
    "XPS M140",
    "XPS M170"
  ]
}
